commonfate/__init__.py
commonfate/__init__.pyc
commonfate/decompose.py
commonfate/decompose.pyc
commonfate/model.py
commonfate/model.pyc
commonfate/transform.py
commonfate/transform.pyc
commonfate/__pycache__/__init__.cpython-35.pyc
commonfate/__pycache__/decompose.cpython-35.pyc
commonfate-0.1.3.dist-info/DESCRIPTION.rst
commonfate-0.1.3.dist-info/METADATA
commonfate-0.1.3.dist-info/RECORD
commonfate-0.1.3.dist-info/WHEEL
commonfate-0.1.3.dist-info/metadata.json
commonfate-0.1.3.dist-info/top_level.txt
